AsyncGear/AsyncPeriod.py
AsyncGear/DataShine.py
AsyncGear/Gear.py
AsyncGear/__init__.py
AsyncGear/method_run_when.py
AsyncGear/run_when.py
AsyncGear-4.7.2.dist-info/LICENSE
AsyncGear-4.7.2.dist-info/METADATA
AsyncGear-4.7.2.dist-info/WHEEL
AsyncGear-4.7.2.dist-info/top_level.txt
AsyncGear-4.7.2.dist-info/RECORD
